Workbook

Sheet Parametros y Costeo
B2: BioPractors — Parámetros de costeo (Plan de Siembra Ley 2173 de 2021)
B3: Celdas azules = valores editables (supuestos). Ajústalos según cotización de vivero y condiciones de la operación.
B5: A. BASE LEGAL
B6: Árboles a sembrar por cada empleado | C6: 2 | E6: Ley 2173/2021 y Res. 1491/2025: mínimo 2 árboles por empleado con contrato vigente al 31-dic del año base. Aplica a medianas y grandes empresas.
B8: B. COSTOS DIRECTOS UNITARIOS POR ÁRBOL (COP)
B9: Material vegetal ~60 cm (árbol/arbusto nativo, vivero registrado ICA) | C9: 12000 | E9: Precio estándar de vivero para material de ~60 cm adaptado a Bogotá y la Sabana (aliso, arrayán, raque, hayuelo, cedro, roble andino, sauco, etc.).
B10: Insumos de siembra (compost/abono, cal dolomita, hidroretenedor, fertilizante inicial, tutor y amarre) | C10: 9000 | E10: Insumos por sitio de plantación.
B11: Mano de obra de siembra (ahoyado 40×40×40, plateo, plantación, tutorado) | C11: 5000 | E11: ≈ jornal $80.000/día ÷ ~16 árboles/día incl. prestaciones y ARL.
B12: Mano de obra de mantenimiento 2 años (operarios: plateo, fertilización, riego, poda, monitoreo) | C12: 14000 | E12: ≈ 10 ciclos en 24 meses (bimestral año 1 / trimestral año 2).
B13: Suministros de mantenimiento 2 años (fertilizante, control fitosanitario, riego, reposición de tutores) | C13: 9000 | E13: Insumos recurrentes durante los 2 años de acompañamiento.
B14: Transporte de operarios y suministros de mantenimiento (por árbol) | C14: 3000 | E14: Movilización de cuadrillas a los sitios durante el mantenimiento.
B16: C. REPOSICIÓN DE ÁRBOLES MUERTOS (PRIMER AÑO)
B17: % de mortalidad a reponer durante el primer año | C17: 0.15 | E17: Reposición exigida por la norma; 15% es un valor conservador de prendimiento en restauración.
B18: Costo de reponer un árbol muerto (material + siembra + insumo básico) | C18: 20000 | E18: =material + mano de obra de resiembra + insumo básico por árbol repuesto.
B19: Costo de reposición prorrateado por árbol sembrado | C19: =C17*C18 | E19: Fórmula: % mortalidad × costo de reposición.
B21: D. FLETE DE MATERIAL VEGETAL (VIVERO → EMPRESA, BOGOTÁ)
B22: Capacidad por viaje — camión 0 a 4 ton (árboles de ~60 cm en bolsa) | C22: 300 | E22: Estimado de unidades por viaje según volumen de bolsa.
B23: Valor del flete por viaje (camión 0-4 ton en Bogotá) | C23: 500000 | E23: Rango de mercado informado: $400.000 a $600.000 por flete. Punto medio $500.000.
B25: E. PARÁMETROS COMERCIALES
B26: Margen / utilidad aplicado sobre el costo directo | C26: 0.5 | E26: Utilidad del 50% sobre el costo directo total (precio = costo × 1,50).
B27: IVA aplicable al servicio | C27: 0.19 | E27: IVA 19%. Verifica el tratamiento tributario; parte del material vegetal puede estar excluido/exento.
B29: COSTO DIRECTO POR ÁRBOL (sin flete de material) | C29: =C9+C10+C11+C12+C13+C14+C19
B30: El flete se calcula aparte por número de viajes (celda C22 y C23).

Sheet Cotizacion
B2: BioPractors | E2: COTIZACIÓN
E3: Plan de Siembra — Ley 2173 de 2021 / Res. 1491 de 2025
E4: Ciudad: Bogotá D.C. y Sabana
C6: Cotización N°: | E6: BP-2026-____
C7: Fecha: | E7: ____ / ____ / 2026
C8: Validez de la oferta: | E8: 30 días calendario
C10: DATOS DEL CLIENTE
C11: Empresa: | E11: ______________________________
C12: NIT: | E12: ______________________________
C13: Contacto: | E13: ______________________________
C15: ► N.° DE EMPLEADOS (único dato pendiente) | E15: 250
C16: Árboles a sembrar (empleados × 2) | E16: =E15*'Parametros y Costeo'!C6
B18: Ítem | C18: Descripción | D18: Cant. (árboles) | E18: Valor unit. (COP/árbol) | F18: Valor total (COP)
B19: 1 | C19: Suministro de material vegetal ~60 cm (nativo, vivero ICA) e instalación: ahoyado, siembra, insumos y tutorado | D19: =E16 | E19: ='Parametros y Costeo'!C9+'Parametros y Costeo'!C10+'Parametros y Costeo'!C11 | F19: =D19*E19
B20: 2 | C20: Mantenimiento y monitoreo por 2 años: operarios (plateo, fertilización, riego, poda) y suministros | D20: =E16 | E20: ='Parametros y Costeo'!C12+'Parametros y Costeo'!C13+'Parametros y Costeo'!C14 | F20: =D20*E20
B21: 3 | C21: Reposición de árboles muertos durante el primer año (prorrateado) | D21: =E16 | E21: ='Parametros y Costeo'!C19 | F21: =D21*E21
B22: 4 | C22: Flete de material vegetal vivero → empresa (camión 0-4 ton). Viajes = árboles ÷ capacidad, redondeado al alza | D22: =ROUNDUP(E16/'Parametros y Costeo'!C22,0) | E22: ='Parametros y Costeo'!C23 | F22: =D22*E22
B23: COSTO DIRECTO TOTAL | F23: =SUM(F19:F22)
B24: Utilidad / margen (50% sobre costo directo) | F24: =F23*'Parametros y Costeo'!C26
B25: SUBTOTAL (antes de IVA) | F25: =F23+F24
B26: IVA (19%) | F26: =F25*'Parametros y Costeo'!C27
B27: VALOR TOTAL DE LA COTIZACIÓN | F27: =F25+F26
C29: Valor por árbol (con IVA): | E29: =F27/E16
C30: Valor por empleado (con IVA): | E30: =F27/E15
B32: ALCANCE Y CONDICIONES
B33: • Cumplimiento de la Ley 2173 de 2021 y la Resolución 1491 de 2025: siembra de 2 árboles por empleado con contrato vigente al 31 de diciembre del año base.
B34: • Material vegetal de ~60 cm proveniente de viveros registrados ante el ICA, con especies nativas adaptadas a Bogotá y la Sabana.
B35: • Incluye establecimiento (ahoyado, siembra, insumos, tutorado), transporte del material y mantenimiento con monitoreo por 24 meses.
B36: • Incluye reposición de árboles muertos durante el primer año (mortalidad estimada 15%).
B37: • El sitio de siembra corresponde a las 'Áreas de Vida' que delimite el municipio/distrito; los costos de permisos o adecuaciones especiales del predio no están incluidos.
B38: • Precios en pesos colombianos (COP). Flete estimado para Bogotá D.C. (camión 0-4 ton); se ajusta según distancia final al predio.
B39: • Valores sujetos a verificación del número de empleados y a visita técnica del predio. Oferta válida por 30 días.
B41: BioPractors — Soluciones ambientales · Bogotá D.C. | Cotización generada como plantilla editable.
